pil_plus.py
pil_plus-0.2.dist-info/METADATA
pil_plus-0.2.dist-info/WHEEL
pil_plus-0.2.dist-info/top_level.txt
pil_plus-0.2.dist-info/RECORD
