Metadata-Version: 2.1
Name: pil-plus
Version: 0.2
Summary: UNKNOWN
Home-page: https://github.com/fahadmaqsood/pil_plus
Author: Fahad Maqsood Qazi
Author-email: qazifahadmaqsood@gmail.com
License: APACHE-2.0
Keywords: PIL,image processing,PIL wrapper,easy PIL,pillow
Platform: UNKNOWN
Requires-Dist: opencv-python
Requires-Dist: pillow
Requires-Dist: matplotlib
Requires-Dist: numpy
Requires-Dist: backgroundremover
